[
  {
    "ma": "MA1",
    "title": "Cylinker 1",
    "image": "image1.jpg",
    "location": {
      "latitude": 15.523231644340704,
      "longitude": 104.4055868099084
    }
  },
  {
    "ma": "MA2",
    "title": "Cylinker 2",
    "image": "image2.jpg",
    "location": {
      "latitude": 22.135235070016883,
      "longitude": 108.76270825127588
    } 
  },
  {
    "ma": "MA3",
    "title": "Cylinker 3",
    "image": "image3.jpg",
    "location": {
      "latitude": 15.193253515600961,
      "longitude": 107.63765448055068
    }
  },
  {
    "ma": "MA4",
    "title": "Cylinker 4",
    "image": "image4.jpg",
    "location": {
      "latitude": 14.04432005747442,
      "longitude": 106.2061795027878
    }
  },
  {
    "ma": "MA5",
    "title": "Cylinker 5",
    "image": "image5.jpg",
    "location": {
      "latitude": 9.794177371192907,
      "longitude": 108.47802475619753
    }
  },
  {
    "ma": "MA6",
    "title": "Cylinker 6",
    "image": "image6.jpg",
    "location": {
      "latitude": 10.095350184391378,
      "longitude": 108.92204894632536
    }
  },
  {
    "ma": "MA7",
    "title": "Cylinker 7",
    "image": "image7.jpg",
    "location": {
      "latitude": 19.41256378948344,
      "longitude": 102.75996482655309
    }
  },
  {
    "ma": "MA8",
    "title": "Cylinker 8",
    "image": "image8.jpg",
    "location": {
      "latitude": 9.99868978313264,
      "longitude": 105.23454476805942
    }
  },
  {
    "ma": "MA9",
    "title": "Cylinker 9",
    "image": "image9.jpg",
    "location": {
      "latitude": 9.686966891798102,
      "longitude": 108.97742443205176
    }
  },
  {
    "ma": "MA10",
    "title": "Cylinker 10",
    "image": "image10.jpg",
    "location": {
      "latitude": 9.083944182941721,
      "longitude": 108.66604039732235
    }
  },
  {
    "ma": "MA11",
    "title": "Cylinker 11",
    "image": "image11.jpg",
    "location": {
      "latitude": 13.294163576179997,
      "longitude": 105.79944582137387
    }
  },
  {
    "ma": "MA12",
    "title": "Cylinker 12",
    "image": "image12.jpg",
    "location": {
      "latitude": 23.04333111954832,
      "longitude": 108.3018129263021
    }
  },
  {
    "ma": "MA13",
    "title": "Cylinker 13",
    "image": "image13.jpg",
    "location": {
      "latitude": 13.61684070880089,
      "longitude": 106.32483979632235
    }
  },
  {
    "ma": "MA14",
    "title": "Cylinker 14",
    "image": "image14.jpg",
    "location": {
      "latitude": 12.603602670595546,
      "longitude": 104.14311790307032
    }
  },
  {
    "ma": "MA15",
    "title": "Cylinker 15",
    "image": "image15.jpg",
    "location": {
      "latitude": 10.924237869145832,
      "longitude": 103.91592818199031
    }
  },
  {
    "ma": "MA16",
    "title": "Cylinker 16",
    "image": "image16.jpg",
    "location": {
      "latitude": 15.750093366962531,
      "longitude": 109.28824612586251
    }
  },
  {
    "ma": "MA17",
    "title": "Cylinker 17",
    "image": "image17.jpg",
    "location": {
      "latitude": 20.31493221355937,
      "longitude": 102.6998321457653
    }
  },
  {
    "ma": "MA18",
    "title": "Cylinker 18",
    "image": "image18.jpg",
    "location": {
      "latitude": 9.843642282660314,
      "longitude": 106.83130128312045
    }
  },
  {
    "ma": "MA19",
    "title": "Cylinker 19",
    "image": "image19.jpg",
    "location": {
      "latitude": 20.882689584204314,
      "longitude": 105.95958684019614
    }
  },
  {
    "ma": "MA20",
    "title": "Cylinker 20",
    "image": "image20.jpg",
    "location": {
      "latitude": 14.119867976693236,
      "longitude": 105.1365425992264
    }
  },
  {
    "ma": "MA21",
    "title": "Cylinker 21",
    "image": "image21.jpg",
    "location": {
      "latitude": 16.240218212775865,
      "longitude": 104.24471852184895
    }
  },
  {
    "ma": "MA22",
    "title": "Cylinker 22",
    "image": "image22.jpg",
    "location": {
      "latitude": 19.905889666602,
      "longitude": 103.18975950872839
    }
  },
  {
    "ma": "MA23",
    "title": "Cylinker 23",
    "image": "image23.jpg",
    "location": {
      "latitude": 12.952757273523815,
      "longitude": 104.55220248297441
    }
  },
  {
    "ma": "MA24",
    "title": "Cylinker 24",
    "image": "image24.jpg",
    "location": {
      "latitude": 11.481110556641756,
      "longitude": 105.30429596717526
    }
  },
  {
    "ma": "MA25",
    "title": "Cylinker 25",
    "image": "image25.jpg",
    "location": {
      "latitude": 9.971839053062457,
      "longitude": 106.6031937037493
    }
  },
  {
    "ma": "MA26",
    "title": "Cylinker 26",
    "image": "image26.jpg",
    "location": {
      "latitude": 20.161230935580154,
      "longitude": 109.22599193428101
    }
  },
  {
    "ma": "MA27",
    "title": "Cylinker 27",
    "image": "image27.jpg",
    "location": {
      "latitude": 20.111005817780025,
      "longitude": 102.59524287769425
    }
  },
  {
    "ma": "MA28",
    "title": "Cylinker 28",
    "image": "image28.jpg",
    "location": {
      "latitude": 21.62454694995586,
      "longitude": 103.00245926642454
    }
  },
  {
    "ma": "MA29",
    "title": "Cylinker 29",
    "image": "image29.jpg",
    "location": {
      "latitude": 10.441853532461028,
      "longitude": 106.18286906628141
    }
  },
  {
    "ma": "MA30",
    "title": "Cylinker 30",
    "image": "image30.jpg",
    "location": {
      "latitude": 17.08192277504014,
      "longitude": 107.26000792014882
    }
  },
  {
    "ma": "MA31",
    "title": "Cylinker 31",
    "image": "image31.jpg",
    "location": {
      "latitude": 12.245179878501261,
      "longitude": 103.90537896222958
    }
  },
  {
    "ma": "MA32",
    "title": "Cylinker 32",
    "image": "image32.jpg",
    "location": {
      "latitude": 18.206386818600016,
      "longitude": 107.08830786796304
    }
  },
  {
    "ma": "MA33",
    "title": "Cylinker 33",
    "image": "image33.jpg",
    "location": {
      "latitude": 18.97580286972007,
      "longitude": 103.74776478145152
    }
  },
  {
    "ma": "MA34",
    "title": "Cylinker 34",
    "image": "image34.jpg",
    "location": {
      "latitude": 11.49703158872461,
      "longitude": 108.51156276554376
    }
  },
  {
    "ma": "MA35",
    "title": "Cylinker 35",
    "image": "image35.jpg",
    "location": {
      "latitude": 8.849198214832755,
      "longitude": 103.99930116568223
    }
  },
  {
    "ma": "MA36",
    "title": "Cylinker 36",
    "image": "image36.jpg",
    "location": {
      "latitude": 12.422644702043556,
      "longitude": 106.43632261534462
    }
  },
  {
    "ma": "MA37",
    "title": "Cylinker 37",
    "image": "image37.jpg",
    "location": {
      "latitude": 21.123066296399692,
      "longitude": 109.4254572830922
    }
  },
  {
    "ma": "MA38",
    "title": "Cylinker 38",
    "image": "image38.jpg",
    "location": {
      "latitude": 13.557603494938009,
      "longitude": 109.24669126567389
    }
  },
  {
    "ma": "MA39",
    "title": "Cylinker 39",
    "image": "image39.jpg",
    "location": {
      "latitude": 13.318502582918892,
      "longitude": 104.42379851086363
    }
  },
  {
    "ma": "MA40",
    "title": "Cylinker 40",
    "image": "image40.jpg",
    "location": {
      "latitude": 22.288552326978575,
      "longitude": 103.41190211414448
    }
  },
  {
    "ma": "MA41",
    "title": "Cylinker 41",
    "image": "image41.jpg",
    "location": {
      "latitude": 10.375651069586498,
      "longitude": 108.9662540435251
    }
  },
  {
    "ma": "MA42",
    "title": "Cylinker 42",
    "image": "image42.jpg",
    "location": {
      "latitude": 9.8031989668916,
      "longitude": 107.8895353572251
    }
  },
  {
    "ma": "MA43",
    "title": "Cylinker 43",
    "image": "image43.jpg",
    "location": {
      "latitude": 11.179917024082265,
      "longitude": 104.95821097029699
    }
  },
  {
    "ma": "MA44",
    "title": "Cylinker 44",
    "image": "image44.jpg",
    "location": {
      "latitude": 17.38125581980197,
      "longitude": 108.3835209080751
    }
  },
  {
    "ma": "MA45",
    "title": "Cylinker 45",
    "image": "image45.jpg",
    "location": {
      "latitude": 11.584406672554335,
      "longitude": 107.40216413931414
    }
  },
  {
    "ma": "MA46",
    "title": "Cylinker 46",
    "image": "image46.jpg",
    "location": {
      "latitude": 16.880044279605645,
      "longitude": 103.7531962420518
    }
  },
  {
    "ma": "MA47",
    "title": "Cylinker 47",
    "image": "image47.jpg",
    "location": {
      "latitude": 9.83108874299016,
      "longitude": 103.36996518122666
    }
  },
  {
    "ma": "MA48",
    "title": "Cylinker 48",
    "image": "image48.jpg",
    "location": {
      "latitude": 21.158262006397276,
      "longitude": 103.31416294027335
    }
  },
  {
    "ma": "MA49",
    "title": "Cylinker 49",
    "image": "image49.jpg",
    "location": {
      "latitude": 11.662327864084327,
      "longitude": 106.71122397871619
    }
  },
  {
    "ma": "MA50",
    "title": "Cylinker 50",
    "image": "image50.jpg",
    "location": {
      "latitude": 19.74415108660993,
      "longitude": 108.57077848476726
    }
  },
  {
    "ma": "MA51",
    "title": "Cylinker 51",
    "image": "image51.jpg",
    "location": {
      "latitude": 23.386132698709243,
      "longitude": 105.57822458177564
    }
  },
  {
    "ma": "MA52",
    "title": "Cylinker 52",
    "image": "image52.jpg",
    "location": {
      "latitude": 11.59764729997617,
      "longitude": 105.73541104238788
    }
  },
  {
    "ma": "MA53",
    "title": "Cylinker 53",
    "image": "image53.jpg",
    "location": {
      "latitude": 17.241332948950664,
      "longitude": 107.56645729078211
    }
  },
  {
    "ma": "MA54",
    "title": "Cylinker 54",
    "image": "image54.jpg",
    "location": {
      "latitude": 8.806149723102205,
      "longitude": 105.40830811318224
    }
  },
  {
    "ma": "MA55",
    "title": "Cylinker 55",
    "image": "image55.jpg",
    "location": {
      "latitude": 9.973118547528937,
      "longitude": 108.62009416918316
    }
  },
  {
    "ma": "MA56",
    "title": "Cylinker 56",
    "image": "image56.jpg",
    "location": {
      "latitude": 12.474863617800082,
      "longitude": 104.54454615363157
    }
  },
  {
    "ma": "MA57",
    "title": "Cylinker 57",
    "image": "image57.jpg",
    "location": {
      "latitude": 12.5348648749369,
      "longitude": 108.53807921904504
    }
  },
  {
    "ma": "MA58",
    "title": "Cylinker 58",
    "image": "image58.jpg",
    "location": {
      "latitude": 15.238879939599112,
      "longitude": 106.33239284602288
    }
  },
  {
    "ma": "MA59",
    "title": "Cylinker 59",
    "image": "image59.jpg",
    "location": {
      "latitude": 14.78522627319522,
      "longitude": 108.14487501602815
    }
  },
  {
    "ma": "MA60",
    "title": "Cylinker 60",
    "image": "image60.jpg",
    "location": {
      "latitude": 19.230111261388892,
      "longitude": 103.33912369114444
    }
  },
  {
    "ma": "MA61",
    "title": "Cylinker 61",
    "image": "image61.jpg",
    "location": {
      "latitude": 21.576151131094186,
      "longitude": 107.25773181029405
    }
  },
  {
    "ma": "MA62",
    "title": "Cylinker 62",
    "image": "image62.jpg",
    "location": {
      "latitude": 10.82577003804269,
      "longitude": 108.92575684890006
    }
  },
  {
    "ma": "MA63",
    "title": "Cylinker 63",
    "image": "image63.jpg",
    "location": {
      "latitude": 10.055153232734446,
      "longitude": 108.8880191022519
    }
  },
  {
    "ma": "MA64",
    "title": "Cylinker 64",
    "image": "image64.jpg",
    "location": {
      "latitude": 8.932942727309255,
      "longitude": 102.33933748039131
    }
  },
  {
    "ma": "MA65",
    "title": "Cylinker 65",
    "image": "image65.jpg",
    "location": {
      "latitude": 19.515875152579724,
      "longitude": 109.16268037790967
    }
  },
  {
    "ma": "MA66",
    "title": "Cylinker 66",
    "image": "image66.jpg",
    "location": {
      "latitude": 13.567041324187628,
      "longitude": 108.83321312052648
    }
  },
  {
    "ma": "MA67",
    "title": "Cylinker 67",
    "image": "image67.jpg",
    "location": {
      "latitude": 22.107637651691515,
      "longitude": 106.95667225578934
    }
  },
  {
    "ma": "MA68",
    "title": "Cylinker 68",
    "image": "image68.jpg",
    "location": {
      "latitude": 9.028574268573376,
      "longitude": 103.94585355003221
    }
  },
  {
    "ma": "MA69",
    "title": "Cylinker 69",
    "image": "image69.jpg",
    "location": {
      "latitude": 12.535644258611072,
      "longitude": 105.28810416585496
    }
  },
  {
    "ma": "MA70",
    "title": "Cylinker 70",
    "image": "image70.jpg",
    "location": {
      "latitude": 11.995984823991648,
      "longitude": 105.25960824022587
    }
  },
  {
    "ma": "MA71",
    "title": "Cylinker 71",
    "image": "image71.jpg",
    "location": {
      "latitude": 16.750144524085268,
      "longitude": 104.58557992891782
    }
  },
  {
    "ma": "MA72",
    "title": "Cylinker 72",
    "image": "image72.jpg",
    "location": {
      "latitude": 11.198567902390575,
      "longitude": 104.00013617517536
    }
  },
  {
    "ma": "MA73",
    "title": "Cylinker 73",
    "image": "image73.jpg",
    "location": {
      "latitude": 19.610367611865648,
      "longitude": 103.08035362230143
    }
  },
  {
    "ma": "MA74",
    "title": "Cylinker 74",
    "image": "image74.jpg",
    "location": {
      "latitude": 12.314329167648852,
      "longitude": 108.48577128969944
    }
  },
  {
    "ma": "MA75",
    "title": "Cylinker 75",
    "image": "image75.jpg",
    "location": {
      "latitude": 8.552469501551522,
      "longitude": 107.18732133376477
    }
  },
  {
    "ma": "MA76",
    "title": "Cylinker 76",
    "image": "image76.jpg",
    "location": {
      "latitude": 13.304445266107912,
      "longitude": 106.53444739272275
    }
  },
  {
    "ma": "MA77",
    "title": "Cylinker 77",
    "image": "image77.jpg",
    "location": {
      "latitude": 18.15907163181295,
      "longitude": 102.23160091486186
    }
  },
  {
    "ma": "MA78",
    "title": "Cylinker 78",
    "image": "image78.jpg",
    "location": {
      "latitude": 18.915488026607875,
      "longitude": 108.18725715208751
    }
  },
  {
    "ma": "MA79",
    "title": "Cylinker 79",
    "image": "image79.jpg",
    "location": {
      "latitude": 14.304010201478953,
      "longitude": 106.73771536147669
    }
  },
  {
    "ma": "MA80",
    "title": "Cylinker 80",
    "image": "image80.jpg",
    "location": {
      "latitude": 19.80625967293006,
      "longitude": 105.35895745396449
    }
  },
  {
    "ma": "MA81",
    "title": "Cylinker 81",
    "image": "image81.jpg",
    "location": {
      "latitude": 19.732460256555694,
      "longitude": 103.48890218416439
    }
  },
  {
    "ma": "MA82",
    "title": "Cylinker 82",
    "image": "image82.jpg",
    "location": {
      "latitude": 20.942745372892077,
      "longitude": 105.55368604875031
    }
  },
  {
    "ma": "MA83",
    "title": "Cylinker 83",
    "image": "image83.jpg",
    "location": {
      "latitude": 13.345490203365976,
      "longitude": 104.80263865040055
    }
  },
  {
    "ma": "MA84",
    "title": "Cylinker 84",
    "image": "image84.jpg",
    "location": {
      "latitude": 11.229094812123463,
      "longitude": 104.2078380959903
    }
  },
  {
    "ma": "MA85",
    "title": "Cylinker 85",
    "image": "image85.jpg",
    "location": {
      "latitude": 16.132788456506333,
      "longitude": 107.8542218804434
    }
  },
  {
    "ma": "MA86",
    "title": "Cylinker 86",
    "image": "image86.jpg",
    "location": {
      "latitude": 11.638517871632505,
      "longitude": 106.01746419807533
    }
  },
  {
    "ma": "MA87",
    "title": "Cylinker 87",
    "image": "image87.jpg",
    "location": {
      "latitude": 12.66515647994653,
      "longitude": 104.9681705087174
    }
  },
  {
    "ma": "MA88",
    "title": "Cylinker 88",
    "image": "image88.jpg",
    "location": {
      "latitude": 11.135420598127844,
      "longitude": 104.74018300338878
    }
  },
  {
    "ma": "MA89",
    "title": "Cylinker 89",
    "image": "image89.jpg",
    "location": {
      "latitude": 19.34315133590544,
      "longitude": 102.72650111815942
    }
  },
  {
    "ma": "MA90",
    "title": "Cylinker 90",
    "image": "image90.jpg",
    "location": {
      "latitude": 8.263683318478156,
      "longitude": 103.46397153399928
    }
  },
  {
    "ma": "MA91",
    "title": "Cylinker 91",
    "image": "image91.jpg",
    "location": {
      "latitude": 23.139989457711415,
      "longitude": 108.26067717615713
    }
  },
  {
    "ma": "MA92",
    "title": "Cylinker 92",
    "image": "image92.jpg",
    "location": {
      "latitude": 19.11130250844431,
      "longitude": 107.14161573801213
    }
  },
  {
    "ma": "MA93",
    "title": "Cylinker 93",
    "image": "image93.jpg",
    "location": {
      "latitude": 20.779972651050578,
      "longitude": 109.014876036043
    }
  },
  {
    "ma": "MA94",
    "title": "Cylinker 94",
    "image": "image94.jpg",
    "location": {
      "latitude": 18.95936777422977,
      "longitude": 104.19874483794541
    }
  },
  {
    "ma": "MA95",
    "title": "Cylinker 95",
    "image": "image95.jpg",
    "location": {
      "latitude": 9.148023031854422,
      "longitude": 108.64374465597314
    }
  },
  {
    "ma": "MA96",
    "title": "Cylinker 96",
    "image": "image96.jpg",
    "location": {
      "latitude": 22.979912242344447,
      "longitude": 106.13571367184532
    }
  },
  {
    "ma": "MA97",
    "title": "Cylinker 97",
    "image": "image97.jpg",
    "location": {
      "latitude": 18.526232583084877,
      "longitude": 103.10375311751
    }
  },
  {
    "ma": "MA98",
    "title": "Cylinker 98",
    "image": "image98.jpg",
    "location": {
      "latitude": 14.723420220795711,
      "longitude": 105.78113629754586
    }
  },
  {
    "ma": "MA99",
    "title": "Cylinker 99",
    "image": "image99.jpg",
    "location": {
      "latitude": 17.505155043918645,
      "longitude": 105.3807804866539
    }
  },
  {
    "ma": "MA100",
    "title": "Cylinker 100",
    "image": "image100.jpg",
    "location": {
      "latitude": 12.459985318360562,
      "longitude": 106.05330084473694
    }
  },
  {
    "ma": "MA101",
    "title": "Cylinker 101",
    "image": "image101.jpg",
    "location": {
      "latitude": 22.205574867035452,
      "longitude": 104.10612369854013
    }
  },
  {
    "ma": "MA102",
    "title": "Cylinker 102",
    "image": "image102.jpg",
    "location": {
      "latitude": 21.906556546258408,
      "longitude": 106.17513479784873
    }
  },
  {
    "ma": "MA103",
    "title": "Cylinker 103",
    "image": "image103.jpg",
    "location": {
      "latitude": 10.597329513341093,
      "longitude": 103.3617925334538
    }
  },
  {
    "ma": "MA104",
    "title": "Cylinker 104",
    "image": "image104.jpg",
    "location": {
      "latitude": 15.55016125772474,
      "longitude": 103.35255283854843
    }
  },
  {
    "ma": "MA105",
    "title": "Cylinker 105",
    "image": "image105.jpg",
    "location": {
      "latitude": 20.563400511611675,
      "longitude": 103.80897507225407
    }
  },
  {
    "ma": "MA106",
    "title": "Cylinker 106",
    "image": "image106.jpg",
    "location": {
      "latitude": 13.935613667663294,
      "longitude": 104.3799426099162
    }
  },
  {
    "ma": "MA107",
    "title": "Cylinker 107",
    "image": "image107.jpg",
    "location": {
      "latitude": 16.788663593926692,
      "longitude": 103.75044728379032
    }
  },
  {
    "ma": "MA108",
    "title": "Cylinker 108",
    "image": "image108.jpg",
    "location": {
      "latitude": 20.62221555194691,
      "longitude": 107.02145778183134
    }
  },
  {
    "ma": "MA109",
    "title": "Cylinker 109",
    "image": "image109.jpg",
    "location": {
      "latitude": 14.78445354474561,
      "longitude": 102.59397139277715
    }
  },
  {
    "ma": "MA110",
    "title": "Cylinker 110",
    "image": "image110.jpg",
    "location": {
      "latitude": 19.87184199419539,
      "longitude": 104.24337763961822
    }
  },
  {
    "ma": "MA111",
    "title": "Cylinker 111",
    "image": "image111.jpg",
    "location": {
      "latitude": 11.49313943743805,
      "longitude": 105.98639360181298
    }
  },
  {
    "ma": "MA112",
    "title": "Cylinker 112",
    "image": "image112.jpg",
    "location": {
      "latitude": 8.461345144478162,
      "longitude": 105.064422822949
    }
  },
  {
    "ma": "MA113",
    "title": "Cylinker 113",
    "image": "image113.jpg",
    "location": {
      "latitude": 22.260980563735615,
      "longitude": 104.82464415211781
    }
  },
  {
    "ma": "MA114",
    "title": "Cylinker 114",
    "image": "image114.jpg",
    "location": {
      "latitude": 20.472794171570307,
      "longitude": 103.02651437711461
    }
  },
  {
    "ma": "MA115",
    "title": "Cylinker 115",
    "image": "image115.jpg",
    "location": {
      "latitude": 15.614077268970528,
      "longitude": 108.9411205650808
    }
  },
  {
    "ma": "MA116",
    "title": "Cylinker 116",
    "image": "image116.jpg",
    "location": {
      "latitude": 13.8373069122206,
      "longitude": 109.40892017715889
    }
  },
  {
    "ma": "MA117",
    "title": "Cylinker 117",
    "image": "image117.jpg",
    "location": {
      "latitude": 16.75393416665142,
      "longitude": 108.82653193824633
    }
  },
  {
    "ma": "MA118",
    "title": "Cylinker 118",
    "image": "image118.jpg",
    "location": {
      "latitude": 9.438857751104575,
      "longitude": 106.51143478369212
    }
  },
  {
    "ma": "MA119",
    "title": "Cylinker 119",
    "image": "image119.jpg",
    "location": {
      "latitude": 22.306152940773263,
      "longitude": 107.18714348424464
    }
  },
  {
    "ma": "MA120",
    "title": "Cylinker 120",
    "image": "image120.jpg",
    "location": {
      "latitude": 17.932681726216714,
      "longitude": 104.52218582284428
    }
  },
  {
    "ma": "MA121",
    "title": "Cylinker 121",
    "image": "image121.jpg",
    "location": {
      "latitude": 16.528473494758536,
      "longitude": 103.19570811251492
    }
  },
  {
    "ma": "MA122",
    "title": "Cylinker 122",
    "image": "image122.jpg",
    "location": {
      "latitude": 9.08817094989027,
      "longitude": 105.44897303182039
    }
  },
  {
    "ma": "MA123",
    "title": "Cylinker 123",
    "image": "image123.jpg",
    "location": {
      "latitude": 15.695557425348063,
      "longitude": 103.67343069563422
    }
  },
  {
    "ma": "MA124",
    "title": "Cylinker 124",
    "image": "image124.jpg",
    "location": {
      "latitude": 10.838366741130523,
      "longitude": 105.1284576079386
    }
  },
  {
    "ma": "MA125",
    "title": "Cylinker 125",
    "image": "image125.jpg",
    "location": {
      "latitude": 9.457935910243704,
      "longitude": 103.48747293623323
    }
  },
  {
    "ma": "MA126",
    "title": "Cylinker 126",
    "image": "image126.jpg",
    "location": {
      "latitude": 13.330217844843403,
      "longitude": 102.12779957176983
    }
  },
  {
    "ma": "MA127",
    "title": "Cylinker 127",
    "image": "image127.jpg",
    "location": {
      "latitude": 13.48059349783698,
      "longitude": 102.52930327749633
    }
  },
  {
    "ma": "MA128",
    "title": "Cylinker 128",
    "image": "image128.jpg",
    "location": {
      "latitude": 9.84675986812347,
      "longitude": 106.88766619085509
    }
  },
  {
    "ma": "MA129",
    "title": "Cylinker 129",
    "image": "image129.jpg",
    "location": {
      "latitude": 19.394008606883318,
      "longitude": 109.27755674968375
    }
  },
  {
    "ma": "MA130",
    "title": "Cylinker 130",
    "image": "image130.jpg",
    "location": {
      "latitude": 14.956059258895168,
      "longitude": 105.072416009629
    }
  },
  {
    "ma": "MA131",
    "title": "Cylinker 131",
    "image": "image131.jpg",
    "location": {
      "latitude": 14.640213314032708,
      "longitude": 103.93448495342304
    }
  },
  {
    "ma": "MA132",
    "title": "Cylinker 132",
    "image": "image132.jpg",
    "location": {
      "latitude": 15.445435432897918,
      "longitude": 102.56786464067697
    }
  },
  {
    "ma": "MA133",
    "title": "Cylinker 133",
    "image": "image133.jpg",
    "location": {
      "latitude": 9.508986970266676,
      "longitude": 104.47453563550201
    }
  },
  {
    "ma": "MA134",
    "title": "Cylinker 134",
    "image": "image134.jpg",
    "location": {
      "latitude": 8.715273635735972,
      "longitude": 108.12046098856588
    }
  },
  {
    "ma": "MA135",
    "title": "Cylinker 135",
    "image": "image135.jpg",
    "location": {
      "latitude": 21.43892178068891,
      "longitude": 104.10389287408643
    }
  },
  {
    "ma": "MA136",
    "title": "Cylinker 136",
    "image": "image136.jpg",
    "location": {
      "latitude": 21.227971344566907,
      "longitude": 102.91321720611069
    }
  },
  {
    "ma": "MA137",
    "title": "Cylinker 137",
    "image": "image137.jpg",
    "location": {
      "latitude": 17.036003704484695,
      "longitude": 108.1599087455003
    }
  },
  {
    "ma": "MA138",
    "title": "Cylinker 138",
    "image": "image138.jpg",
    "location": {
      "latitude": 11.455500467627978,
      "longitude": 105.51059749555736
    }
  },
  {
    "ma": "MA139",
    "title": "Cylinker 139",
    "image": "image139.jpg",
    "location": {
      "latitude": 16.081398469252424,
      "longitude": 104.04901651744984
    }
  },
  {
    "ma": "MA140",
    "title": "Cylinker 140",
    "image": "image140.jpg",
    "location": {
      "latitude": 22.712605365774536,
      "longitude": 108.46236585331089
    }
  },
  {
    "ma": "MA141",
    "title": "Cylinker 141",
    "image": "image141.jpg",
    "location": {
      "latitude": 17.33713208961055,
      "longitude": 106.76238095888377
    }
  },
  {
    "ma": "MA142",
    "title": "Cylinker 142",
    "image": "image142.jpg",
    "location": {
      "latitude": 22.847700528796896,
      "longitude": 106.40244033837321
    }
  },
  {
    "ma": "MA143",
    "title": "Cylinker 143",
    "image": "image143.jpg",
    "location": {
      "latitude": 16.17392024364949,
      "longitude": 104.42588242705843
    }
  },
  {
    "ma": "MA144",
    "title": "Cylinker 144",
    "image": "image144.jpg",
    "location": {
      "latitude": 16.965997711716483,
      "longitude": 103.1957883185556
    }
  },
  {
    "ma": "MA145",
    "title": "Cylinker 145",
    "image": "image145.jpg",
    "location": {
      "latitude": 8.270507298578224,
      "longitude": 102.99981044907749
    }
  },
  {
    "ma": "MA146",
    "title": "Cylinker 146",
    "image": "image146.jpg",
    "location": {
      "latitude": 12.257889051959513,
      "longitude": 104.6129471770473
    }
  },
  {
    "ma": "MA147",
    "title": "Cylinker 147",
    "image": "image147.jpg",
    "location": {
      "latitude": 16.1344221319524,
      "longitude": 102.21012199249
    }
  },
  {
    "ma": "MA148",
    "title": "Cylinker 148",
    "image": "image148.jpg",
    "location": {
      "latitude": 17.43244849749972,
      "longitude": 105.1160338596904
    }
  },
  {
    "ma": "MA149",
    "title": "Cylinker 149",
    "image": "image149.jpg",
    "location": {
      "latitude": 22.490640951342527,
      "longitude": 102.12340922354518
    }
  },
  {
    "ma": "MA150",
    "title": "Cylinker 150",
    "image": "image150.jpg",
    "location": {
      "latitude": 22.072399607873685,
      "longitude": 103.0764793635113
    }
  },
  {
    "ma": "MA151",
    "title": "Cylinker 151",
    "image": "image151.jpg",
    "location": {
      "latitude": 9.862496061825095,
      "longitude": 106.42687667319
    }
  },
  {
    "ma": "MA152",
    "title": "Cylinker 152",
    "image": "image152.jpg",
    "location": {
      "latitude": 22.374087733506713,
      "longitude": 103.86368463346875
    }
  },
  {
    "ma": "MA153",
    "title": "Cylinker 153",
    "image": "image153.jpg",
    "location": {
      "latitude": 9.88269237821397,
      "longitude": 105.87769669741739
    }
  },
  {
    "ma": "MA154",
    "title": "Cylinker 154",
    "image": "image154.jpg",
    "location": {
      "latitude": 20.66328018833998,
      "longitude": 102.9171805246976
    }
  },
  {
    "ma": "MA155",
    "title": "Cylinker 155",
    "image": "image155.jpg",
    "location": {
      "latitude": 15.663613421577837,
      "longitude": 104.37786259238153
    }
  },
  {
    "ma": "MA156",
    "title": "Cylinker 156",
    "image": "image156.jpg",
    "location": {
      "latitude": 19.075267488686755,
      "longitude": 104.34129092878031
    }
  },
  {
    "ma": "MA157",
    "title": "Cylinker 157",
    "image": "image157.jpg",
    "location": {
      "latitude": 8.789718251973717,
      "longitude": 103.43039093912999
    }
  },
  {
    "ma": "MA158",
    "title": "Cylinker 158",
    "image": "image158.jpg",
    "location": {
      "latitude": 8.884717206345071,
      "longitude": 103.20248392895954
    }
  },
  {
    "ma": "MA159",
    "title": "Cylinker 159",
    "image": "image159.jpg",
    "location": {
      "latitude": 9.919648424515255,
      "longitude": 106.21885631348958
    }
  },
  {
    "ma": "MA160",
    "title": "Cylinker 160",
    "image": "image160.jpg",
    "location": {
      "latitude": 22.036497704193614,
      "longitude": 107.61628502498137
    }
  },
  {
    "ma": "MA161",
    "title": "Cylinker 161",
    "image": "image161.jpg",
    "location": {
      "latitude": 20.23760297189044,
      "longitude": 105.03930467540881
    }
  },
  {
    "ma": "MA162",
    "title": "Cylinker 162",
    "image": "image162.jpg",
    "location": {
      "latitude": 18.44790070180384,
      "longitude": 102.24709724195527
    }
  },
  {
    "ma": "MA163",
    "title": "Cylinker 163",
    "image": "image163.jpg",
    "location": {
      "latitude": 12.82831439572739,
      "longitude": 107.82988297100391
    }
  },
  {
    "ma": "MA164",
    "title": "Cylinker 164",
    "image": "image164.jpg",
    "location": {
      "latitude": 19.456232360373214,
      "longitude": 103.17928020305274
    }
  },
  {
    "ma": "MA165",
    "title": "Cylinker 165",
    "image": "image165.jpg",
    "location": {
      "latitude": 10.325241459040567,
      "longitude": 104.87273759675496
    }
  },
  {
    "ma": "MA166",
    "title": "Cylinker 166",
    "image": "image166.jpg",
    "location": {
      "latitude": 13.958440221943063,
      "longitude": 107.60172661979571
    }
  },
  {
    "ma": "MA167",
    "title": "Cylinker 167",
    "image": "image167.jpg",
    "location": {
      "latitude": 20.847291838349186,
      "longitude": 105.89539371837482
    }
  },
  {
    "ma": "MA168",
    "title": "Cylinker 168",
    "image": "image168.jpg",
    "location": {
      "latitude": 18.180667865401148,
      "longitude": 106.96587822281552
    }
  },
  {
    "ma": "MA169",
    "title": "Cylinker 169",
    "image": "image169.jpg",
    "location": {
      "latitude": 10.438398630120465,
      "longitude": 103.36600751914754
    }
  },
  {
    "ma": "MA170",
    "title": "Cylinker 170",
    "image": "image170.jpg",
    "location": {
      "latitude": 23.15297252968398,
      "longitude": 103.11774466390857
    }
  },
  {
    "ma": "MA171",
    "title": "Cylinker 171",
    "image": "image171.jpg",
    "location": {
      "latitude": 22.250209510641646,
      "longitude": 108.72957818954872
    }
  },
  {
    "ma": "MA172",
    "title": "Cylinker 172",
    "image": "image172.jpg",
    "location": {
      "latitude": 21.758739913635708,
      "longitude": 108.941322788069
    }
  },
  {
    "ma": "MA173",
    "title": "Cylinker 173",
    "image": "image173.jpg",
    "location": {
      "latitude": 14.772957095162404,
      "longitude": 108.87687783464973
    }
  },
  {
    "ma": "MA174",
    "title": "Cylinker 174",
    "image": "image174.jpg",
    "location": {
      "latitude": 16.889269035113337,
      "longitude": 105.6997905652389
    }
  },
  {
    "ma": "MA175",
    "title": "Cylinker 175",
    "image": "image175.jpg",
    "location": {
      "latitude": 9.313897295798906,
      "longitude": 104.58420340139266
    }
  },
  {
    "ma": "MA176",
    "title": "Cylinker 176",
    "image": "image176.jpg",
    "location": {
      "latitude": 13.912850846868771,
      "longitude": 109.21242724175806
    }
  },
  {
    "ma": "MA177",
    "title": "Cylinker 177",
    "image": "image177.jpg",
    "location": {
      "latitude": 13.690478421356703,
      "longitude": 108.96591652391835
    }
  },
  {
    "ma": "MA178",
    "title": "Cylinker 178",
    "image": "image178.jpg",
    "location": {
      "latitude": 15.778366405088324,
      "longitude": 103.16181748854264
    }
  },
  {
    "ma": "MA179",
    "title": "Cylinker 179",
    "image": "image179.jpg",
    "location": {
      "latitude": 8.758159649178038,
      "longitude": 105.93934391580531
    }
  },
  {
    "ma": "MA180",
    "title": "Cylinker 180",
    "image": "image180.jpg",
    "location": {
      "latitude": 17.41936957389898,
      "longitude": 103.79449935802847
    }
  },
  {
    "ma": "MA181",
    "title": "Cylinker 181",
    "image": "image181.jpg",
    "location": {
      "latitude": 9.72876622070044,
      "longitude": 103.72437996653628
    }
  },
  {
    "ma": "MA182",
    "title": "Cylinker 182",
    "image": "image182.jpg",
    "location": {
      "latitude": 14.13973828890319,
      "longitude": 106.93275836207147
    }
  },
  {
    "ma": "MA183",
    "title": "Cylinker 183",
    "image": "image183.jpg",
    "location": {
      "latitude": 12.292543514108841,
      "longitude": 103.30361502767677
    }
  },
  {
    "ma": "MA184",
    "title": "Cylinker 184",
    "image": "image184.jpg",
    "location": {
      "latitude": 16.0280938824219,
      "longitude": 107.66373453922785
    }
  },
  {
    "ma": "MA185",
    "title": "Cylinker 185",
    "image": "image185.jpg",
    "location": {
      "latitude": 21.861685304632843,
      "longitude": 107.51497709094694
    }
  },
  {
    "ma": "MA186",
    "title": "Cylinker 186",
    "image": "image186.jpg",
    "location": {
      "latitude": 19.334316265816053,
      "longitude": 107.16554215975626
    }
  },
  {
    "ma": "MA187",
    "title": "Cylinker 187",
    "image": "image187.jpg",
    "location": {
      "latitude": 9.248332631989712,
      "longitude": 103.1269416500992
    }
  },
  {
    "ma": "MA188",
    "title": "Cylinker 188",
    "image": "image188.jpg",
    "location": {
      "latitude": 21.428187425983644,
      "longitude": 102.76368277238483
    }
  },
  {
    "ma": "MA189",
    "title": "Cylinker 189",
    "image": "image189.jpg",
    "location": {
      "latitude": 9.0751067860773,
      "longitude": 109.08823317894043
    }
  },
  {
    "ma": "MA190",
    "title": "Cylinker 190",
    "image": "image190.jpg",
    "location": {
      "latitude": 13.506061966902362,
      "longitude": 107.00969939670374
    }
  },
  {
    "ma": "MA191",
    "title": "Cylinker 191",
    "image": "image191.jpg",
    "location": {
      "latitude": 13.224876898074111,
      "longitude": 104.44102487751893
    }
  },
  {
    "ma": "MA192",
    "title": "Cylinker 192",
    "image": "image192.jpg",
    "location": {
      "latitude": 19.251051818935007,
      "longitude": 102.55752988159635
    }
  },
  {
    "ma": "MA193",
    "title": "Cylinker 193",
    "image": "image193.jpg",
    "location": {
      "latitude": 15.42380498920113,
      "longitude": 106.76060385156373
    }
  },
  {
    "ma": "MA194",
    "title": "Cylinker 194",
    "image": "image194.jpg",
    "location": {
      "latitude": 10.180567888178182,
      "longitude": 108.57670199722945
    }
  },
  {
    "ma": "MA195",
    "title": "Cylinker 195",
    "image": "image195.jpg",
    "location": {
      "latitude": 22.37499156529885,
      "longitude": 109.4025022265267
    }
  },
  {
    "ma": "MA196",
    "title": "Cylinker 196",
    "image": "image196.jpg",
    "location": {
      "latitude": 13.940902663314668,
      "longitude": 106.78784625517923
    }
  },
  {
    "ma": "MA197",
    "title": "Cylinker 197",
    "image": "image197.jpg",
    "location": {
      "latitude": 8.458672595335669,
      "longitude": 107.20135775058611
    }
  },
  {
    "ma": "MA198",
    "title": "Cylinker 198",
    "image": "image198.jpg",
    "location": {
      "latitude": 11.58821196356666,
      "longitude": 105.2967172987307
    }
  },
  {
    "ma": "MA199",
    "title": "Cylinker 199",
    "image": "image199.jpg",
    "location": {
      "latitude": 9.141692691559879,
      "longitude": 106.8021807506271
    }
  },
  {
    "ma": "MA200",
    "title": "Cylinker 200",
    "image": "image200.jpg",
    "location": {
      "latitude": 15.009441434246465,
      "longitude": 103.27372357685631
    }
  },
  {
    "ma": "MA201",
    "title": "Cylinker 201",
    "image": "image201.jpg",
    "location": {
      "latitude": 10.537032633589165,
      "longitude": 106.75616956395059
    }
  },
  {
    "ma": "MA202",
    "title": "Cylinker 202",
    "image": "image202.jpg",
    "location": {
      "latitude": 8.9132529510497,
      "longitude": 102.48977621045826
    }
  },
  {
    "ma": "MA203",
    "title": "Cylinker 203",
    "image": "image203.jpg",
    "location": {
      "latitude": 9.234280795402917,
      "longitude": 107.19117915359718
    }
  },
  {
    "ma": "MA204",
    "title": "Cylinker 204",
    "image": "image204.jpg",
    "location": {
      "latitude": 12.028917190091677,
      "longitude": 109.3827933475479
    }
  },
  {
    "ma": "MA205",
    "title": "Cylinker 205",
    "image": "image205.jpg",
    "location": {
      "latitude": 18.045999837306233,
      "longitude": 102.76067849509327
    }
  },
  {
    "ma": "MA206",
    "title": "Cylinker 206",
    "image": "image206.jpg",
    "location": {
      "latitude": 18.775505073595127,
      "longitude": 102.60615110872035
    }
  },
  {
    "ma": "MA207",
    "title": "Cylinker 207",
    "image": "image207.jpg",
    "location": {
      "latitude": 16.667966493637778,
      "longitude": 103.92212906211088
    }
  },
  {
    "ma": "MA208",
    "title": "Cylinker 208",
    "image": "image208.jpg",
    "location": {
      "latitude": 19.006650501553782,
      "longitude": 102.13197042149356
    }
  },
  {
    "ma": "MA209",
    "title": "Cylinker 209",
    "image": "image209.jpg",
    "location": {
      "latitude": 9.709238428792661,
      "longitude": 108.42819700544194
    }
  },
  {
    "ma": "MA210",
    "title": "Cylinker 210",
    "image": "image210.jpg",
    "location": {
      "latitude": 19.010490868206666,
      "longitude": 106.23693876117036
    }
  },
  {
    "ma": "MA211",
    "title": "Cylinker 211",
    "image": "image211.jpg",
    "location": {
      "latitude": 16.2006956316879,
      "longitude": 103.90725743702423
    }
  },
  {
    "ma": "MA212",
    "title": "Cylinker 212",
    "image": "image212.jpg",
    "location": {
      "latitude": 12.865695696665586,
      "longitude": 108.94008220784129
    }
  },
  {
    "ma": "MA213",
    "title": "Cylinker 213",
    "image": "image213.jpg",
    "location": {
      "latitude": 11.104110422124991,
      "longitude": 107.225119608804
    }
  },
  {
    "ma": "MA214",
    "title": "Cylinker 214",
    "image": "image214.jpg",
    "location": {
      "latitude": 16.62378834977723,
      "longitude": 108.04979946307515
    }
  },
  {
    "ma": "MA215",
    "title": "Cylinker 215",
    "image": "image215.jpg",
    "location": {
      "latitude": 12.24428589851927,
      "longitude": 106.21191849921878
    }
  },
  {
    "ma": "MA216",
    "title": "Cylinker 216",
    "image": "image216.jpg",
    "location": {
      "latitude": 19.776577629226068,
      "longitude": 105.63227107247606
    }
  },
  {
    "ma": "MA217",
    "title": "Cylinker 217",
    "image": "image217.jpg",
    "location": {
      "latitude": 11.857789411037889,
      "longitude": 106.64549797996067
    }
  },
  {
    "ma": "MA218",
    "title": "Cylinker 218",
    "image": "image218.jpg",
    "location": {
      "latitude": 9.311350938452616,
      "longitude": 107.36205361632368
    }
  },
  {
    "ma": "MA219",
    "title": "Cylinker 219",
    "image": "image219.jpg",
    "location": {
      "latitude": 21.644803166877658,
      "longitude": 105.7178262227058
    }
  },
  {
    "ma": "MA220",
    "title": "Cylinker 220",
    "image": "image220.jpg",
    "location": {
      "latitude": 8.638786821222995,
      "longitude": 103.35903825327834
    }
  },
  {
    "ma": "MA221",
    "title": "Cylinker 221",
    "image": "image221.jpg",
    "location": {
      "latitude": 15.314241101389843,
      "longitude": 106.85315148523914
    }
  },
  {
    "ma": "MA222",
    "title": "Cylinker 222",
    "image": "image222.jpg",
    "location": {
      "latitude": 10.248120302475439,
      "longitude": 103.85788049677123
    }
  },
  {
    "ma": "MA223",
    "title": "Cylinker 223",
    "image": "image223.jpg",
    "location": {
      "latitude": 9.776552324990185,
      "longitude": 105.96334716560465
    }
  },
  {
    "ma": "MA224",
    "title": "Cylinker 224",
    "image": "image224.jpg",
    "location": {
      "latitude": 21.485321599787703,
      "longitude": 107.61738157409805
    }
  },
  {
    "ma": "MA225",
    "title": "Cylinker 225",
    "image": "image225.jpg",
    "location": {
      "latitude": 14.096752464397126,
      "longitude": 104.18520310731078
    }
  },
  {
    "ma": "MA226",
    "title": "Cylinker 226",
    "image": "image226.jpg",
    "location": {
      "latitude": 16.662174445861297,
      "longitude": 103.14645678397429
    }
  },
  {
    "ma": "MA227",
    "title": "Cylinker 227",
    "image": "image227.jpg",
    "location": {
      "latitude": 10.966595440905525,
      "longitude": 104.67511067637516
    }
  },
  {
    "ma": "MA228",
    "title": "Cylinker 228",
    "image": "image228.jpg",
    "location": {
      "latitude": 15.848695121643399,
      "longitude": 102.45453543333798
    }
  },
  {
    "ma": "MA229",
    "title": "Cylinker 229",
    "image": "image229.jpg",
    "location": {
      "latitude": 21.251250027086826,
      "longitude": 106.84008552630809
    }
  },
  {
    "ma": "MA230",
    "title": "Cylinker 230",
    "image": "image230.jpg",
    "location": {
      "latitude": 8.215980714692872,
      "longitude": 106.50826155097336
    }
  },
  {
    "ma": "MA231",
    "title": "Cylinker 231",
    "image": "image231.jpg",
    "location": {
      "latitude": 14.913689170381383,
      "longitude": 106.05342137976166
    }
  },
  {
    "ma": "MA232",
    "title": "Cylinker 232",
    "image": "image232.jpg",
    "location": {
      "latitude": 21.837874899657685,
      "longitude": 103.49310637665724
    }
  },
  {
    "ma": "MA233",
    "title": "Cylinker 233",
    "image": "image233.jpg",
    "location": {
      "latitude": 20.60997660970876,
      "longitude": 108.62663216927447
    }
  },
  {
    "ma": "MA234",
    "title": "Cylinker 234",
    "image": "image234.jpg",
    "location": {
      "latitude": 21.152884048060926,
      "longitude": 104.55480067835123
    }
  },
  {
    "ma": "MA235",
    "title": "Cylinker 235",
    "image": "image235.jpg",
    "location": {
      "latitude": 17.125647432854493,
      "longitude": 107.65314045862563
    }
  },
  {
    "ma": "MA236",
    "title": "Cylinker 236",
    "image": "image236.jpg",
    "location": {
      "latitude": 10.187726101555096,
      "longitude": 104.84059244881125
    }
  },
  {
    "ma": "MA237",
    "title": "Cylinker 237",
    "image": "image237.jpg",
    "location": {
      "latitude": 20.679771698447183,
      "longitude": 108.82815145187399
    }
  },
  {
    "ma": "MA238",
    "title": "Cylinker 238",
    "image": "image238.jpg",
    "location": {
      "latitude": 10.137997431967046,
      "longitude": 105.41044552354062
    }
  },
  {
    "ma": "MA239",
    "title": "Cylinker 239",
    "image": "image239.jpg",
    "location": {
      "latitude": 14.748893688567303,
      "longitude": 103.54476836995345
    }
  },
  {
    "ma": "MA240",
    "title": "Cylinker 240",
    "image": "image240.jpg",
    "location": {
      "latitude": 14.34498493334527,
      "longitude": 107.75407201173537
    }
  },
  {
    "ma": "MA241",
    "title": "Cylinker 241",
    "image": "image241.jpg",
    "location": {
      "latitude": 10.704738864618037,
      "longitude": 105.20243642136026
    }
  },
  {
    "ma": "MA242",
    "title": "Cylinker 242",
    "image": "image242.jpg",
    "location": {
      "latitude": 21.759799409334803,
      "longitude": 107.66138793152098
    }
  },
  {
    "ma": "MA243",
    "title": "Cylinker 243",
    "image": "image243.jpg",
    "location": {
      "latitude": 21.629030771934968,
      "longitude": 104.6180684079559
    }
  },
  {
    "ma": "MA244",
    "title": "Cylinker 244",
    "image": "image244.jpg",
    "location": {
      "latitude": 16.187970908982987,
      "longitude": 108.51506597525439
    }
  },
  {
    "ma": "MA245",
    "title": "Cylinker 245",
    "image": "image245.jpg",
    "location": {
      "latitude": 15.586693849417008,
      "longitude": 105.12318971303989
    }
  },
  {
    "ma": "MA246",
    "title": "Cylinker 246",
    "image": "image246.jpg",
    "location": {
      "latitude": 21.559967446984388,
      "longitude": 107.88702212546535
    }
  },
  {
    "ma": "MA247",
    "title": "Cylinker 247",
    "image": "image247.jpg",
    "location": {
      "latitude": 12.12642268621554,
      "longitude": 105.54839705508195
    }
  },
  {
    "ma": "MA248",
    "title": "Cylinker 248",
    "image": "image248.jpg",
    "location": {
      "latitude": 13.589619282641372,
      "longitude": 108.61888760305511
    }
  },
  {
    "ma": "MA249",
    "title": "Cylinker 249",
    "image": "image249.jpg",
    "location": {
      "latitude": 13.92995179267853,
      "longitude": 107.89983183483804
    }
  },
  {
    "ma": "MA250",
    "title": "Cylinker 250",
    "image": "image250.jpg",
    "location": {
      "latitude": 8.618289852313254,
      "longitude": 104.26521955164444
    }
  },
  {
    "ma": "MA251",
    "title": "Cylinker 251",
    "image": "image251.jpg",
    "location": {
      "latitude": 19.718245448647266,
      "longitude": 107.97049632685085
    }
  },
  {
    "ma": "MA252",
    "title": "Cylinker 252",
    "image": "image252.jpg",
    "location": {
      "latitude": 22.10388600165101,
      "longitude": 104.21719703753676
    }
  },
  {
    "ma": "MA253",
    "title": "Cylinker 253",
    "image": "image253.jpg",
    "location": {
      "latitude": 15.661432126235663,
      "longitude": 105.71627198770864
    }
  },
  {
    "ma": "MA254",
    "title": "Cylinker 254",
    "image": "image254.jpg",
    "location": {
      "latitude": 9.686839476536313,
      "longitude": 105.8919912677272
    }
  },
  {
    "ma": "MA255",
    "title": "Cylinker 255",
    "image": "image255.jpg",
    "location": {
      "latitude": 8.291663794971846,
      "longitude": 102.91372189307937
    }
  },
  {
    "ma": "MA256",
    "title": "Cylinker 256",
    "image": "image256.jpg",
    "location": {
      "latitude": 12.647019241158558,
      "longitude": 106.02669442221004
    }
  },
  {
    "ma": "MA257",
    "title": "Cylinker 257",
    "image": "image257.jpg",
    "location": {
      "latitude": 20.256677710306686,
      "longitude": 103.69204743656695
    }
  },
  {
    "ma": "MA258",
    "title": "Cylinker 258",
    "image": "image258.jpg",
    "location": {
      "latitude": 23.36857483403157,
      "longitude": 107.75554913773414
    }
  },
  {
    "ma": "MA259",
    "title": "Cylinker 259",
    "image": "image259.jpg",
    "location": {
      "latitude": 10.712504165089666,
      "longitude": 102.1145836053641
    }
  },
  {
    "ma": "MA260",
    "title": "Cylinker 260",
    "image": "image260.jpg",
    "location": {
      "latitude": 12.348452019003975,
      "longitude": 105.77888508791246
    }
  },
  {
    "ma": "MA261",
    "title": "Cylinker 261",
    "image": "image261.jpg",
    "location": {
      "latitude": 9.085646046868678,
      "longitude": 107.14642880593098
    }
  },
  {
    "ma": "MA262",
    "title": "Cylinker 262",
    "image": "image262.jpg",
    "location": {
      "latitude": 12.358777532967146,
      "longitude": 106.28683713400756
    }
  },
  {
    "ma": "MA263",
    "title": "Cylinker 263",
    "image": "image263.jpg",
    "location": {
      "latitude": 20.674619040849763,
      "longitude": 105.6560291135875
    }
  },
  {
    "ma": "MA264",
    "title": "Cylinker 264",
    "image": "image264.jpg",
    "location": {
      "latitude": 10.890851003549457,
      "longitude": 103.41789359777343
    }
  },
  {
    "ma": "MA265",
    "title": "Cylinker 265",
    "image": "image265.jpg",
    "location": {
      "latitude": 12.544395779304311,
      "longitude": 108.78497214502268
    }
  },
  {
    "ma": "MA266",
    "title": "Cylinker 266",
    "image": "image266.jpg",
    "location": {
      "latitude": 11.467849386571,
      "longitude": 104.61853953771619
    }
  },
  {
    "ma": "MA267",
    "title": "Cylinker 267",
    "image": "image267.jpg",
    "location": {
      "latitude": 11.5507923652258,
      "longitude": 102.65457911435364
    }
  },
  {
    "ma": "MA268",
    "title": "Cylinker 268",
    "image": "image268.jpg",
    "location": {
      "latitude": 22.8376532039743,
      "longitude": 105.23625273519264
    }
  },
  {
    "ma": "MA269",
    "title": "Cylinker 269",
    "image": "image269.jpg",
    "location": {
      "latitude": 19.32084097875972,
      "longitude": 108.9565454097507
    }
  },
  {
    "ma": "MA270",
    "title": "Cylinker 270",
    "image": "image270.jpg",
    "location": {
      "latitude": 22.913380909062187,
      "longitude": 106.52657520909271
    }
  },
  {
    "ma": "MA271",
    "title": "Cylinker 271",
    "image": "image271.jpg",
    "location": {
      "latitude": 16.8466655682439,
      "longitude": 105.66097022824391
    }
  },
  {
    "ma": "MA272",
    "title": "Cylinker 272",
    "image": "image272.jpg",
    "location": {
      "latitude": 22.290750463066413,
      "longitude": 103.64748794294339
    }
  },
  {
    "ma": "MA273",
    "title": "Cylinker 273",
    "image": "image273.jpg",
    "location": {
      "latitude": 11.219226204612223,
      "longitude": 104.58100039784115
    }
  },
  {
    "ma": "MA274",
    "title": "Cylinker 274",
    "image": "image274.jpg",
    "location": {
      "latitude": 17.294623552457246,
      "longitude": 106.38136720294672
    }
  },
  {
    "ma": "MA275",
    "title": "Cylinker 275",
    "image": "image275.jpg",
    "location": {
      "latitude": 20.55236982530112,
      "longitude": 107.76895290629128
    }
  },
  {
    "ma": "MA276",
    "title": "Cylinker 276",
    "image": "image276.jpg",
    "location": {
      "latitude": 21.718359984018836,
      "longitude": 104.96178603000159
    }
  },
  {
    "ma": "MA277",
    "title": "Cylinker 277",
    "image": "image277.jpg",
    "location": {
      "latitude": 21.98504455164629,
      "longitude": 104.64066059383984
    }
  },
  {
    "ma": "MA278",
    "title": "Cylinker 278",
    "image": "image278.jpg",
    "location": {
      "latitude": 12.291337551155985,
      "longitude": 106.01455143559448
    }
  },
  {
    "ma": "MA279",
    "title": "Cylinker 279",
    "image": "image279.jpg",
    "location": {
      "latitude": 22.29748406237733,
      "longitude": 108.05369830787944
    }
  },
  {
    "ma": "MA280",
    "title": "Cylinker 280",
    "image": "image280.jpg",
    "location": {
      "latitude": 20.468313948245914,
      "longitude": 102.42005417884421
    }
  },
  {
    "ma": "MA281",
    "title": "Cylinker 281",
    "image": "image281.jpg",
    "location": {
      "latitude": 8.235856879029344,
      "longitude": 107.14678322948092
    }
  },
  {
    "ma": "MA282",
    "title": "Cylinker 282",
    "image": "image282.jpg",
    "location": {
      "latitude": 12.663434982863237,
      "longitude": 106.0246598061474
    }
  },
  {
    "ma": "MA283",
    "title": "Cylinker 283",
    "image": "image283.jpg",
    "location": {
      "latitude": 14.471030738907512,
      "longitude": 105.57558540673331
    }
  },
  {
    "ma": "MA284",
    "title": "Cylinker 284",
    "image": "image284.jpg",
    "location": {
      "latitude": 11.56769962794025,
      "longitude": 106.56319085682789
    }
  },
  {
    "ma": "MA285",
    "title": "Cylinker 285",
    "image": "image285.jpg",
    "location": {
      "latitude": 19.042167234822486,
      "longitude": 108.33547807501391
    }
  },
  {
    "ma": "MA286",
    "title": "Cylinker 286",
    "image": "image286.jpg",
    "location": {
      "latitude": 21.78869304093714,
      "longitude": 102.73485876513735
    }
  },
  {
    "ma": "MA287",
    "title": "Cylinker 287",
    "image": "image287.jpg",
    "location": {
      "latitude": 12.240934986512375,
      "longitude": 107.79618843864526
    }
  },
  {
    "ma": "MA288",
    "title": "Cylinker 288",
    "image": "image288.jpg",
    "location": {
      "latitude": 13.63995868928557,
      "longitude": 102.64242315964204
    }
  },
  {
    "ma": "MA289",
    "title": "Cylinker 289",
    "image": "image289.jpg",
    "location": {
      "latitude": 23.300430639225873,
      "longitude": 103.54576079601725
    }
  },
  {
    "ma": "MA290",
    "title": "Cylinker 290",
    "image": "image290.jpg",
    "location": {
      "latitude": 16.360904706128046,
      "longitude": 104.0583357801546
    }
  },
  {
    "ma": "MA291",
    "title": "Cylinker 291",
    "image": "image291.jpg",
    "location": {
      "latitude": 11.463106319375768,
      "longitude": 106.3511135171267
    }
  },
  {
    "ma": "MA292",
    "title": "Cylinker 292",
    "image": "image292.jpg",
    "location": {
      "latitude": 19.54112892120682,
      "longitude": 103.17856183894405
    }
  },
  {
    "ma": "MA293",
    "title": "Cylinker 293",
    "image": "image293.jpg",
    "location": {
      "latitude": 11.008827632400283,
      "longitude": 103.23318020182252
    }
  },
  {
    "ma": "MA294",
    "title": "Cylinker 294",
    "image": "image294.jpg",
    "location": {
      "latitude": 12.175672105007308,
      "longitude": 109.29560756005763
    }
  },
  {
    "ma": "MA295",
    "title": "Cylinker 295",
    "image": "image295.jpg",
    "location": {
      "latitude": 18.428242650910093,
      "longitude": 105.09767216171808
    }
  },
  {
    "ma": "MA296",
    "title": "Cylinker 296",
    "image": "image296.jpg",
    "location": {
      "latitude": 13.085381451278517,
      "longitude": 105.43891118005259
    }
  },
  {
    "ma": "MA297",
    "title": "Cylinker 297",
    "image": "image297.jpg",
    "location": {
      "latitude": 16.36740498454396,
      "longitude": 105.90524517496068
    }
  },
  {
    "ma": "MA298",
    "title": "Cylinker 298",
    "image": "image298.jpg",
    "location": {
      "latitude": 17.76519085944331,
      "longitude": 108.70930694653885
    }
  },
  {
    "ma": "MA299",
    "title": "Cylinker 299",
    "image": "image299.jpg",
    "location": {
      "latitude": 16.26112522443333,
      "longitude": 103.6037463338662
    }
  },
  {
    "ma": "MA300",
    "title": "Cylinker 300",
    "image": "image300.jpg",
    "location": {
      "latitude": 14.255544843721296,
      "longitude": 103.79712222837463
    }
  },
  {
    "ma": "MA301",
    "title": "Cylinker 301",
    "image": "image301.jpg",
    "location": {
      "latitude": 14.989609846632288,
      "longitude": 102.85299539518282
    }
  },
  {
    "ma": "MA302",
    "title": "Cylinker 302",
    "image": "image302.jpg",
    "location": {
      "latitude": 9.409498329783348,
      "longitude": 103.60295054706508
    }
  },
  {
    "ma": "MA303",
    "title": "Cylinker 303",
    "image": "image303.jpg",
    "location": {
      "latitude": 17.86202105318871,
      "longitude": 106.75604650941493
    }
  },
  {
    "ma": "MA304",
    "title": "Cylinker 304",
    "image": "image304.jpg",
    "location": {
      "latitude": 11.311483778196216,
      "longitude": 108.77167016804277
    }
  },
  {
    "ma": "MA305",
    "title": "Cylinker 305",
    "image": "image305.jpg",
    "location": {
      "latitude": 23.04881839982562,
      "longitude": 107.15377871356195
    }
  },
  {
    "ma": "MA306",
    "title": "Cylinker 306",
    "image": "image306.jpg",
    "location": {
      "latitude": 17.204368353147505,
      "longitude": 107.68608956069194
    }
  },
  {
    "ma": "MA307",
    "title": "Cylinker 307",
    "image": "image307.jpg",
    "location": {
      "latitude": 23.364453756008913,
      "longitude": 108.48292738775694
    }
  },
  {
    "ma": "MA308",
    "title": "Cylinker 308",
    "image": "image308.jpg",
    "location": {
      "latitude": 16.525690653773314,
      "longitude": 104.34881866483578
    }
  },
  {
    "ma": "MA309",
    "title": "Cylinker 309",
    "image": "image309.jpg",
    "location": {
      "latitude": 15.942081548160715,
      "longitude": 103.39138009097583
    }
  },
  {
    "ma": "MA310",
    "title": "Cylinker 310",
    "image": "image310.jpg",
    "location": {
      "latitude": 13.930683737865593,
      "longitude": 106.58480966287803
    }
  },
  {
    "ma": "MA311",
    "title": "Cylinker 311",
    "image": "image311.jpg",
    "location": {
      "latitude": 16.463997683837665,
      "longitude": 109.1786269446567
    }
  },
  {
    "ma": "MA312",
    "title": "Cylinker 312",
    "image": "image312.jpg",
    "location": {
      "latitude": 9.528898701057019,
      "longitude": 102.17444530453386
    }
  },
  {
    "ma": "MA313",
    "title": "Cylinker 313",
    "image": "image313.jpg",
    "location": {
      "latitude": 22.887587823640185,
      "longitude": 106.3692562297041
    }
  },
  {
    "ma": "MA314",
    "title": "Cylinker 314",
    "image": "image314.jpg",
    "location": {
      "latitude": 20.319846967547612,
      "longitude": 106.44502256380258
    }
  },
  {
    "ma": "MA315",
    "title": "Cylinker 315",
    "image": "image315.jpg",
    "location": {
      "latitude": 9.908671592235864,
      "longitude": 106.29430685002413
    }
  },
  {
    "ma": "MA316",
    "title": "Cylinker 316",
    "image": "image316.jpg",
    "location": {
      "latitude": 8.511134448980489,
      "longitude": 106.02387442190985
    }
  },
  {
    "ma": "MA317",
    "title": "Cylinker 317",
    "image": "image317.jpg",
    "location": {
      "latitude": 18.19184810410452,
      "longitude": 104.07923075068551
    }
  },
  {
    "ma": "MA318",
    "title": "Cylinker 318",
    "image": "image318.jpg",
    "location": {
      "latitude": 16.219063087418,
      "longitude": 108.1077487904185
    }
  },
  {
    "ma": "MA319",
    "title": "Cylinker 319",
    "image": "image319.jpg",
    "location": {
      "latitude": 8.5639297353314,
      "longitude": 102.75217598200115
    }
  },
  {
    "ma": "MA320",
    "title": "Cylinker 320",
    "image": "image320.jpg",
    "location": {
      "latitude": 16.55004716706633,
      "longitude": 108.89131158145697
    }
  },
  {
    "ma": "MA321",
    "title": "Cylinker 321",
    "image": "image321.jpg",
    "location": {
      "latitude": 22.551387993718336,
      "longitude": 103.49899396102639
    }
  },
  {
    "ma": "MA322",
    "title": "Cylinker 322",
    "image": "image322.jpg",
    "location": {
      "latitude": 10.349708944534783,
      "longitude": 104.84988548525857
    }
  },
  {
    "ma": "MA323",
    "title": "Cylinker 323",
    "image": "image323.jpg",
    "location": {
      "latitude": 12.917256058643513,
      "longitude": 107.34609415232245
    }
  },
  {
    "ma": "MA324",
    "title": "Cylinker 324",
    "image": "image324.jpg",
    "location": {
      "latitude": 19.731370846993848,
      "longitude": 105.94483819049485
    }
  },
  {
    "ma": "MA325",
    "title": "Cylinker 325",
    "image": "image325.jpg",
    "location": {
      "latitude": 12.74700020435938,
      "longitude": 106.59447843989554
    }
  },
  {
    "ma": "MA326",
    "title": "Cylinker 326",
    "image": "image326.jpg",
    "location": {
      "latitude": 16.994135956138503,
      "longitude": 107.87363686634336
    }
  },
  {
    "ma": "MA327",
    "title": "Cylinker 327",
    "image": "image327.jpg",
    "location": {
      "latitude": 8.464801742453291,
      "longitude": 106.2054843484252
    }
  },
  {
    "ma": "MA328",
    "title": "Cylinker 328",
    "image": "image328.jpg",
    "location": {
      "latitude": 10.19846789882045,
      "longitude": 102.87112300781759
    }
  },
  {
    "ma": "MA329",
    "title": "Cylinker 329",
    "image": "image329.jpg",
    "location": {
      "latitude": 22.02683503376013,
      "longitude": 107.17754703908363
    }
  },
  {
    "ma": "MA330",
    "title": "Cylinker 330",
    "image": "image330.jpg",
    "location": {
      "latitude": 14.495299565927674,
      "longitude": 106.15334228603302
    }
  },
  {
    "ma": "MA331",
    "title": "Cylinker 331",
    "image": "image331.jpg",
    "location": {
      "latitude": 21.556349039542415,
      "longitude": 106.01138658649141
    }
  },
  {
    "ma": "MA332",
    "title": "Cylinker 332",
    "image": "image332.jpg",
    "location": {
      "latitude": 9.847515793966256,
      "longitude": 104.43978468183656
    }
  },
  {
    "ma": "MA333",
    "title": "Cylinker 333",
    "image": "image333.jpg",
    "location": {
      "latitude": 15.337821943324041,
      "longitude": 103.05441440130687
    }
  },
  {
    "ma": "MA334",
    "title": "Cylinker 334",
    "image": "image334.jpg",
    "location": {
      "latitude": 10.11266298122967,
      "longitude": 105.01558839637322
    }
  },
  {
    "ma": "MA335",
    "title": "Cylinker 335",
    "image": "image335.jpg",
    "location": {
      "latitude": 20.70264960937937,
      "longitude": 103.7344262751354
    }
  },
  {
    "ma": "MA336",
    "title": "Cylinker 336",
    "image": "image336.jpg",
    "location": {
      "latitude": 8.778134145282955,
      "longitude": 104.45898692543841
    }
  },
  {
    "ma": "MA337",
    "title": "Cylinker 337",
    "image": "image337.jpg",
    "location": {
      "latitude": 22.597558082921054,
      "longitude": 108.66531196570457
    }
  },
  {
    "ma": "MA338",
    "title": "Cylinker 338",
    "image": "image338.jpg",
    "location": {
      "latitude": 13.815930074188287,
      "longitude": 107.00781166382485
    }
  },
  {
    "ma": "MA339",
    "title": "Cylinker 339",
    "image": "image339.jpg",
    "location": {
      "latitude": 20.147543109037827,
      "longitude": 102.8119562003547
    }
  },
  {
    "ma": "MA340",
    "title": "Cylinker 340",
    "image": "image340.jpg",
    "location": {
      "latitude": 11.776841701266404,
      "longitude": 103.22234109243931
    }
  },
  {
    "ma": "MA341",
    "title": "Cylinker 341",
    "image": "image341.jpg",
    "location": {
      "latitude": 11.590747992392064,
      "longitude": 105.84204463821466
    }
  },
  {
    "ma": "MA342",
    "title": "Cylinker 342",
    "image": "image342.jpg",
    "location": {
      "latitude": 10.715349850705895,
      "longitude": 109.2650144204321
    }
  },
  {
    "ma": "MA343",
    "title": "Cylinker 343",
    "image": "image343.jpg",
    "location": {
      "latitude": 12.533962926388774,
      "longitude": 107.2539884791393
    }
  },
  {
    "ma": "MA344",
    "title": "Cylinker 344",
    "image": "image344.jpg",
    "location": {
      "latitude": 10.49356206259077,
      "longitude": 108.23879216553271
    }
  },
  {
    "ma": "MA345",
    "title": "Cylinker 345",
    "image": "image345.jpg",
    "location": {
      "latitude": 15.12361917254534,
      "longitude": 107.21426356638463
    }
  },
  {
    "ma": "MA346",
    "title": "Cylinker 346",
    "image": "image346.jpg",
    "location": {
      "latitude": 9.417826796367109,
      "longitude": 107.00465266678664
    }
  },
  {
    "ma": "MA347",
    "title": "Cylinker 347",
    "image": "image347.jpg",
    "location": {
      "latitude": 21.83346315225824,
      "longitude": 105.16291760107593
    }
  },
  {
    "ma": "MA348",
    "title": "Cylinker 348",
    "image": "image348.jpg",
    "location": {
      "latitude": 9.04555832608676,
      "longitude": 107.52762555608456
    }
  },
  {
    "ma": "MA349",
    "title": "Cylinker 349",
    "image": "image349.jpg",
    "location": {
      "latitude": 18.41580704948823,
      "longitude": 102.37349356275371
    }
  },
  {
    "ma": "MA350",
    "title": "Cylinker 350",
    "image": "image350.jpg",
    "location": {
      "latitude": 9.481461537478493,
      "longitude": 106.78403758032218
    }
  },
  {
    "ma": "MA351",
    "title": "Cylinker 351",
    "image": "image351.jpg",
    "location": {
      "latitude": 15.271828774318504,
      "longitude": 103.40941481342217
    }
  },
  {
    "ma": "MA352",
    "title": "Cylinker 352",
    "image": "image352.jpg",
    "location": {
      "latitude": 14.739402474738512,
      "longitude": 108.6880152750382
    }
  },
  {
    "ma": "MA353",
    "title": "Cylinker 353",
    "image": "image353.jpg",
    "location": {
      "latitude": 9.685168825206581,
      "longitude": 102.36587023733794
    }
  },
  {
    "ma": "MA354",
    "title": "Cylinker 354",
    "image": "image354.jpg",
    "location": {
      "latitude": 16.57233997987928,
      "longitude": 105.36021793858329
    }
  },
  {
    "ma": "MA355",
    "title": "Cylinker 355",
    "image": "image355.jpg",
    "location": {
      "latitude": 12.67485919490667,
      "longitude": 107.82021059462207
    }
  },
  {
    "ma": "MA356",
    "title": "Cylinker 356",
    "image": "image356.jpg",
    "location": {
      "latitude": 19.811235878835987,
      "longitude": 108.86985109240915
    }
  },
  {
    "ma": "MA357",
    "title": "Cylinker 357",
    "image": "image357.jpg",
    "location": {
      "latitude": 15.495332259095498,
      "longitude": 108.66039150931506
    }
  },
  {
    "ma": "MA358",
    "title": "Cylinker 358",
    "image": "image358.jpg",
    "location": {
      "latitude": 20.582855357397094,
      "longitude": 103.50588134319443
    }
  },
  {
    "ma": "MA359",
    "title": "Cylinker 359",
    "image": "image359.jpg",
    "location": {
      "latitude": 11.0374335699256,
      "longitude": 106.74375867179214
    }
  },
  {
    "ma": "MA360",
    "title": "Cylinker 360",
    "image": "image360.jpg",
    "location": {
      "latitude": 22.834512327859017,
      "longitude": 102.2445615320759
    }
  },
  {
    "ma": "MA361",
    "title": "Cylinker 361",
    "image": "image361.jpg",
    "location": {
      "latitude": 18.882785681954694,
      "longitude": 107.60723610446202
    }
  },
  {
    "ma": "MA362",
    "title": "Cylinker 362",
    "image": "image362.jpg",
    "location": {
      "latitude": 12.831707096563367,
      "longitude": 102.77299207454726
    }
  },
  {
    "ma": "MA363",
    "title": "Cylinker 363",
    "image": "image363.jpg",
    "location": {
      "latitude": 23.348156771746062,
      "longitude": 109.40203304358809
    }
  },
  {
    "ma": "MA364",
    "title": "Cylinker 364",
    "image": "image364.jpg",
    "location": {
      "latitude": 21.734185662033276,
      "longitude": 105.29023044966286
    }
  },
  {
    "ma": "MA365",
    "title": "Cylinker 365",
    "image": "image365.jpg",
    "location": {
      "latitude": 16.968267843920025,
      "longitude": 104.12387922203597
    }
  },
  {
    "ma": "MA366",
    "title": "Cylinker 366",
    "image": "image366.jpg",
    "location": {
      "latitude": 15.005784455185289,
      "longitude": 105.31608439153906
    }
  },
  {
    "ma": "MA367",
    "title": "Cylinker 367",
    "image": "image367.jpg",
    "location": {
      "latitude": 13.999397109606358,
      "longitude": 108.98925253105752
    }
  },
  {
    "ma": "MA368",
    "title": "Cylinker 368",
    "image": "image368.jpg",
    "location": {
      "latitude": 21.604722421784267,
      "longitude": 106.07465835524489
    }
  },
  {
    "ma": "MA369",
    "title": "Cylinker 369",
    "image": "image369.jpg",
    "location": {
      "latitude": 22.211114766744274,
      "longitude": 106.68478635666831
    }
  },
  {
    "ma": "MA370",
    "title": "Cylinker 370",
    "image": "image370.jpg",
    "location": {
      "latitude": 20.688490906705027,
      "longitude": 106.10611423654404
    }
  },
  {
    "ma": "MA371",
    "title": "Cylinker 371",
    "image": "image371.jpg",
    "location": {
      "latitude": 10.802333788067056,
      "longitude": 104.49407754428358
    }
  },
  {
    "ma": "MA372",
    "title": "Cylinker 372",
    "image": "image372.jpg",
    "location": {
      "latitude": 11.85930014566043,
      "longitude": 104.13624732320676
    }
  },
  {
    "ma": "MA373",
    "title": "Cylinker 373",
    "image": "image373.jpg",
    "location": {
      "latitude": 13.831324362602338,
      "longitude": 103.86465400323921
    }
  },
  {
    "ma": "MA374",
    "title": "Cylinker 374",
    "image": "image374.jpg",
    "location": {
      "latitude": 20.900690319335908,
      "longitude": 105.29860564244922
    }
  },
  {
    "ma": "MA375",
    "title": "Cylinker 375",
    "image": "image375.jpg",
    "location": {
      "latitude": 8.217916381812701,
      "longitude": 106.01217874962872
    }
  },
  {
    "ma": "MA376",
    "title": "Cylinker 376",
    "image": "image376.jpg",
    "location": {
      "latitude": 17.155405551925753,
      "longitude": 106.00125217173046
    }
  },
  {
    "ma": "MA377",
    "title": "Cylinker 377",
    "image": "image377.jpg",
    "location": {
      "latitude": 17.19845181162627,
      "longitude": 108.99607253046122
    }
  },
  {
    "ma": "MA378",
    "title": "Cylinker 378",
    "image": "image378.jpg",
    "location": {
      "latitude": 22.51649886077485,
      "longitude": 105.04311944691185
    }
  },
  {
    "ma": "MA379",
    "title": "Cylinker 379",
    "image": "image379.jpg",
    "location": {
      "latitude": 11.304254714383397,
      "longitude": 103.75689182626859
    }
  },
  {
    "ma": "MA380",
    "title": "Cylinker 380",
    "image": "image380.jpg",
    "location": {
      "latitude": 20.5507136736048,
      "longitude": 105.36981186895252
    }
  },
  {
    "ma": "MA381",
    "title": "Cylinker 381",
    "image": "image381.jpg",
    "location": {
      "latitude": 8.364512744934139,
      "longitude": 107.6648418884487
    }
  },
  {
    "ma": "MA382",
    "title": "Cylinker 382",
    "image": "image382.jpg",
    "location": {
      "latitude": 21.348886424572328,
      "longitude": 108.05049801083628
    }
  },
  {
    "ma": "MA383",
    "title": "Cylinker 383",
    "image": "image383.jpg",
    "location": {
      "latitude": 14.563849178905944,
      "longitude": 102.68614699430242
    }
  },
  {
    "ma": "MA384",
    "title": "Cylinker 384",
    "image": "image384.jpg",
    "location": {
      "latitude": 16.359894872652035,
      "longitude": 103.97791989008772
    }
  },
  {
    "ma": "MA385",
    "title": "Cylinker 385",
    "image": "image385.jpg",
    "location": {
      "latitude": 21.32942278780903,
      "longitude": 108.96124493425017
    }
  },
  {
    "ma": "MA386",
    "title": "Cylinker 386",
    "image": "image386.jpg",
    "location": {
      "latitude": 21.927089116997767,
      "longitude": 102.42016883411621
    }
  },
  {
    "ma": "MA387",
    "title": "Cylinker 387",
    "image": "image387.jpg",
    "location": {
      "latitude": 22.962642242577907,
      "longitude": 105.48348814187712
    }
  },
  {
    "ma": "MA388",
    "title": "Cylinker 388",
    "image": "image388.jpg",
    "location": {
      "latitude": 14.422270777264977,
      "longitude": 104.36124921176578
    }
  },
  {
    "ma": "MA389",
    "title": "Cylinker 389",
    "image": "image389.jpg",
    "location": {
      "latitude": 15.488421425097815,
      "longitude": 103.90660537530181
    }
  },
  {
    "ma": "MA390",
    "title": "Cylinker 390",
    "image": "image390.jpg",
    "location": {
      "latitude": 23.315046579193172,
      "longitude": 108.90576005708493
    }
  },
  {
    "ma": "MA391",
    "title": "Cylinker 391",
    "image": "image391.jpg",
    "location": {
      "latitude": 10.525241543708779,
      "longitude": 103.5327930374156
    }
  },
  {
    "ma": "MA392",
    "title": "Cylinker 392",
    "image": "image392.jpg",
    "location": {
      "latitude": 15.14541705060217,
      "longitude": 108.46688878862845
    }
  },
  {
    "ma": "MA393",
    "title": "Cylinker 393",
    "image": "image393.jpg",
    "location": {
      "latitude": 8.952286832501462,
      "longitude": 108.80045976568621
    }
  },
  {
    "ma": "MA394",
    "title": "Cylinker 394",
    "image": "image394.jpg",
    "location": {
      "latitude": 21.923981944097378,
      "longitude": 106.6315774577082
    }
  },
  {
    "ma": "MA395",
    "title": "Cylinker 395",
    "image": "image395.jpg",
    "location": {
      "latitude": 11.812165096797314,
      "longitude": 108.59003027285833
    }
  },
  {
    "ma": "MA396",
    "title": "Cylinker 396",
    "image": "image396.jpg",
    "location": {
      "latitude": 14.260900862252939,
      "longitude": 107.64101286547285
    }
  },
  {
    "ma": "MA397",
    "title": "Cylinker 397",
    "image": "image397.jpg",
    "location": {
      "latitude": 9.733107784674967,
      "longitude": 109.13107598635128
    }
  },
  {
    "ma": "MA398",
    "title": "Cylinker 398",
    "image": "image398.jpg",
    "location": {
      "latitude": 12.237751291616274,
      "longitude": 104.9937388305134
    }
  },
  {
    "ma": "MA399",
    "title": "Cylinker 399",
    "image": "image399.jpg",
    "location": {
      "latitude": 21.927975061736028,
      "longitude": 103.55162400236523
    }
  },
  {
    "ma": "MA400",
    "title": "Cylinker 400",
    "image": "image400.jpg",
    "location": {
      "latitude": 12.378853696735515,
      "longitude": 102.55652563253398
    }
  },
  {
    "ma": "MA401",
    "title": "Cylinker 401",
    "image": "image401.jpg",
    "location": {
      "latitude": 18.161980790695075,
      "longitude": 104.5664614110018
    }
  },
  {
    "ma": "MA402",
    "title": "Cylinker 402",
    "image": "image402.jpg",
    "location": {
      "latitude": 12.441499567656827,
      "longitude": 106.25814184715537
    }
  },
  {
    "ma": "MA403",
    "title": "Cylinker 403",
    "image": "image403.jpg",
    "location": {
      "latitude": 21.80803712643508,
      "longitude": 107.33177178138865
    }
  },
  {
    "ma": "MA404",
    "title": "Cylinker 404",
    "image": "image404.jpg",
    "location": {
      "latitude": 17.100201183182044,
      "longitude": 108.8436546791347
    }
  },
  {
    "ma": "MA405",
    "title": "Cylinker 405",
    "image": "image405.jpg",
    "location": {
      "latitude": 9.518014136549697,
      "longitude": 103.97840232083543
    }
  },
  {
    "ma": "MA406",
    "title": "Cylinker 406",
    "image": "image406.jpg",
    "location": {
      "latitude": 22.332699081068558,
      "longitude": 106.4680461493904
    }
  },
  {
    "ma": "MA407",
    "title": "Cylinker 407",
    "image": "image407.jpg",
    "location": {
      "latitude": 15.228086293519345,
      "longitude": 106.41806821312386
    }
  },
  {
    "ma": "MA408",
    "title": "Cylinker 408",
    "image": "image408.jpg",
    "location": {
      "latitude": 21.570913710836706,
      "longitude": 103.61363955158087
    }
  },
  {
    "ma": "MA409",
    "title": "Cylinker 409",
    "image": "image409.jpg",
    "location": {
      "latitude": 13.044493948926632,
      "longitude": 108.37682770029653
    }
  },
  {
    "ma": "MA410",
    "title": "Cylinker 410",
    "image": "image410.jpg",
    "location": {
      "latitude": 23.07748083791686,
      "longitude": 107.28133024910056
    }
  },
  {
    "ma": "MA411",
    "title": "Cylinker 411",
    "image": "image411.jpg",
    "location": {
      "latitude": 15.658031642393807,
      "longitude": 102.8378034852549
    }
  },
  {
    "ma": "MA412",
    "title": "Cylinker 412",
    "image": "image412.jpg",
    "location": {
      "latitude": 14.911763340518867,
      "longitude": 106.80164177940772
    }
  },
  {
    "ma": "MA413",
    "title": "Cylinker 413",
    "image": "image413.jpg",
    "location": {
      "latitude": 10.688024099028176,
      "longitude": 103.19478512377452
    }
  },
  {
    "ma": "MA414",
    "title": "Cylinker 414",
    "image": "image414.jpg",
    "location": {
      "latitude": 10.304958964360257,
      "longitude": 106.51907438943445
    }
  },
  {
    "ma": "MA415",
    "title": "Cylinker 415",
    "image": "image415.jpg",
    "location": {
      "latitude": 22.631559218347796,
      "longitude": 107.8959057002431
    }
  },
  {
    "ma": "MA416",
    "title": "Cylinker 416",
    "image": "image416.jpg",
    "location": {
      "latitude": 12.58313259963387,
      "longitude": 104.2319371936186
    }
  },
  {
    "ma": "MA417",
    "title": "Cylinker 417",
    "image": "image417.jpg",
    "location": {
      "latitude": 10.967881359289612,
      "longitude": 108.49545070060137
    }
  },
  {
    "ma": "MA418",
    "title": "Cylinker 418",
    "image": "image418.jpg",
    "location": {
      "latitude": 21.740803409302213,
      "longitude": 105.95194106663557
    }
  },
  {
    "ma": "MA419",
    "title": "Cylinker 419",
    "image": "image419.jpg",
    "location": {
      "latitude": 15.142377815806011,
      "longitude": 107.62194088387415
    }
  },
  {
    "ma": "MA420",
    "title": "Cylinker 420",
    "image": "image420.jpg",
    "location": {
      "latitude": 16.17646138853593,
      "longitude": 107.26657982405617
    }
  },
  {
    "ma": "MA421",
    "title": "Cylinker 421",
    "image": "image421.jpg",
    "location": {
      "latitude": 20.515940157683374,
      "longitude": 106.48858935408659
    }
  },
  {
    "ma": "MA422",
    "title": "Cylinker 422",
    "image": "image422.jpg",
    "location": {
      "latitude": 8.45085676834249,
      "longitude": 102.40567388966879
    }
  },
  {
    "ma": "MA423",
    "title": "Cylinker 423",
    "image": "image423.jpg",
    "location": {
      "latitude": 17.105964806398674,
      "longitude": 108.417219998913
    }
  },
  {
    "ma": "MA424",
    "title": "Cylinker 424",
    "image": "image424.jpg",
    "location": {
      "latitude": 19.153156312546926,
      "longitude": 102.16594889118926
    }
  },
  {
    "ma": "MA425",
    "title": "Cylinker 425",
    "image": "image425.jpg",
    "location": {
      "latitude": 11.486998319288647,
      "longitude": 106.0776022732839
    }
  },
  {
    "ma": "MA426",
    "title": "Cylinker 426",
    "image": "image426.jpg",
    "location": {
      "latitude": 21.972915040965994,
      "longitude": 105.52916454277997
    }
  },
  {
    "ma": "MA427",
    "title": "Cylinker 427",
    "image": "image427.jpg",
    "location": {
      "latitude": 13.094934509648771,
      "longitude": 104.25858924315614
    }
  },
  {
    "ma": "MA428",
    "title": "Cylinker 428",
    "image": "image428.jpg",
    "location": {
      "latitude": 22.916916631566117,
      "longitude": 103.3834801666784
    }
  },
  {
    "ma": "MA429",
    "title": "Cylinker 429",
    "image": "image429.jpg",
    "location": {
      "latitude": 12.72819645681087,
      "longitude": 105.13502748680563
    }
  },
  {
    "ma": "MA430",
    "title": "Cylinker 430",
    "image": "image430.jpg",
    "location": {
      "latitude": 9.001912504255175,
      "longitude": 104.13752553607605
    }
  },
  {
    "ma": "MA431",
    "title": "Cylinker 431",
    "image": "image431.jpg",
    "location": {
      "latitude": 13.004109574294919,
      "longitude": 103.08912445562623
    }
  },
  {
    "ma": "MA432",
    "title": "Cylinker 432",
    "image": "image432.jpg",
    "location": {
      "latitude": 21.052059523252225,
      "longitude": 107.57349413099242
    }
  },
  {
    "ma": "MA433",
    "title": "Cylinker 433",
    "image": "image433.jpg",
    "location": {
      "latitude": 22.507931911561588,
      "longitude": 108.60160179244434
    }
  },
  {
    "ma": "MA434",
    "title": "Cylinker 434",
    "image": "image434.jpg",
    "location": {
      "latitude": 14.714046127883623,
      "longitude": 107.95365084142037
    }
  },
  {
    "ma": "MA435",
    "title": "Cylinker 435",
    "image": "image435.jpg",
    "location": {
      "latitude": 14.87333259394385,
      "longitude": 102.45112935097902
    }
  },
  {
    "ma": "MA436",
    "title": "Cylinker 436",
    "image": "image436.jpg",
    "location": {
      "latitude": 14.329184249850023,
      "longitude": 103.86900669229728
    }
  },
  {
    "ma": "MA437",
    "title": "Cylinker 437",
    "image": "image437.jpg",
    "location": {
      "latitude": 18.725258680687695,
      "longitude": 103.4368096460251
    }
  },
  {
    "ma": "MA438",
    "title": "Cylinker 438",
    "image": "image438.jpg",
    "location": {
      "latitude": 16.562077756963838,
      "longitude": 107.42499305923054
    }
  },
  {
    "ma": "MA439",
    "title": "Cylinker 439",
    "image": "image439.jpg",
    "location": {
      "latitude": 16.07293454150832,
      "longitude": 103.77027985528146
    }
  },
  {
    "ma": "MA440",
    "title": "Cylinker 440",
    "image": "image440.jpg",
    "location": {
      "latitude": 9.895412160237266,
      "longitude": 108.6918403849451
    }
  },
  {
    "ma": "MA441",
    "title": "Cylinker 441",
    "image": "image441.jpg",
    "location": {
      "latitude": 17.515068097252346,
      "longitude": 107.60069827340192
    }
  },
  {
    "ma": "MA442",
    "title": "Cylinker 442",
    "image": "image442.jpg",
    "location": {
      "latitude": 14.600545067541862,
      "longitude": 107.42037529543245
    }
  },
  {
    "ma": "MA443",
    "title": "Cylinker 443",
    "image": "image443.jpg",
    "location": {
      "latitude": 13.496244460311246,
      "longitude": 106.26320434487708
    }
  },
  {
    "ma": "MA444",
    "title": "Cylinker 444",
    "image": "image444.jpg",
    "location": {
      "latitude": 9.973351268938657,
      "longitude": 107.85749399266837
    }
  },
  {
    "ma": "MA445",
    "title": "Cylinker 445",
    "image": "image445.jpg",
    "location": {
      "latitude": 15.657416384224113,
      "longitude": 108.64529962163118
    }
  },
  {
    "ma": "MA446",
    "title": "Cylinker 446",
    "image": "image446.jpg",
    "location": {
      "latitude": 21.578610076848122,
      "longitude": 103.83728189770693
    }
  },
  {
    "ma": "MA447",
    "title": "Cylinker 447",
    "image": "image447.jpg",
    "location": {
      "latitude": 19.107328504501325,
      "longitude": 102.63653662525441
    }
  },
  {
    "ma": "MA448",
    "title": "Cylinker 448",
    "image": "image448.jpg",
    "location": {
      "latitude": 8.571082219957702,
      "longitude": 106.90385450879852
    }
  },
  {
    "ma": "MA449",
    "title": "Cylinker 449",
    "image": "image449.jpg",
    "location": {
      "latitude": 13.612596205610778,
      "longitude": 107.4899772283526
    }
  },
  {
    "ma": "MA450",
    "title": "Cylinker 450",
    "image": "image450.jpg",
    "location": {
      "latitude": 17.306795494503483,
      "longitude": 108.7815743293028
    }
  },
  {
    "ma": "MA451",
    "title": "Cylinker 451",
    "image": "image451.jpg",
    "location": {
      "latitude": 23.181365457004667,
      "longitude": 109.49567473056655
    }
  },
  {
    "ma": "MA452",
    "title": "Cylinker 452",
    "image": "image452.jpg",
    "location": {
      "latitude": 16.34091723302204,
      "longitude": 102.25328962082816
    }
  },
  {
    "ma": "MA453",
    "title": "Cylinker 453",
    "image": "image453.jpg",
    "location": {
      "latitude": 18.683654356867955,
      "longitude": 107.97914160056789
    }
  },
  {
    "ma": "MA454",
    "title": "Cylinker 454",
    "image": "image454.jpg",
    "location": {
      "latitude": 16.507806856106154,
      "longitude": 106.8404572934175
    }
  },
  {
    "ma": "MA455",
    "title": "Cylinker 455",
    "image": "image455.jpg",
    "location": {
      "latitude": 16.6601848936961,
      "longitude": 108.77540372374328
    }
  },
  {
    "ma": "MA456",
    "title": "Cylinker 456",
    "image": "image456.jpg",
    "location": {
      "latitude": 10.801951121463041,
      "longitude": 103.73533788940574
    }
  },
  {
    "ma": "MA457",
    "title": "Cylinker 457",
    "image": "image457.jpg",
    "location": {
      "latitude": 13.206100490023601,
      "longitude": 109.46360481198873
    }
  },
  {
    "ma": "MA458",
    "title": "Cylinker 458",
    "image": "image458.jpg",
    "location": {
      "latitude": 12.470145568068649,
      "longitude": 106.25668771009104
    }
  },
  {
    "ma": "MA459",
    "title": "Cylinker 459",
    "image": "image459.jpg",
    "location": {
      "latitude": 8.40508690745358,
      "longitude": 104.76208303359293
    }
  },
  {
    "ma": "MA460",
    "title": "Cylinker 460",
    "image": "image460.jpg",
    "location": {
      "latitude": 8.629534393003878,
      "longitude": 107.82768911592463
    }
  },
  {
    "ma": "MA461",
    "title": "Cylinker 461",
    "image": "image461.jpg",
    "location": {
      "latitude": 21.549079562076265,
      "longitude": 108.0920905299792
    }
  },
  {
    "ma": "MA462",
    "title": "Cylinker 462",
    "image": "image462.jpg",
    "location": {
      "latitude": 12.421188522366569,
      "longitude": 108.00287737578851
    }
  },
  {
    "ma": "MA463",
    "title": "Cylinker 463",
    "image": "image463.jpg",
    "location": {
      "latitude": 8.840119518351674,
      "longitude": 108.32734385836474
    }
  },
  {
    "ma": "MA464",
    "title": "Cylinker 464",
    "image": "image464.jpg",
    "location": {
      "latitude": 13.711031208898419,
      "longitude": 103.14743226450031
    }
  },
  {
    "ma": "MA465",
    "title": "Cylinker 465",
    "image": "image465.jpg",
    "location": {
      "latitude": 8.986549257706933,
      "longitude": 106.24634843010033
    }
  },
  {
    "ma": "MA466",
    "title": "Cylinker 466",
    "image": "image466.jpg",
    "location": {
      "latitude": 18.796614988201746,
      "longitude": 105.21536239496079
    }
  },
  {
    "ma": "MA467",
    "title": "Cylinker 467",
    "image": "image467.jpg",
    "location": {
      "latitude": 8.427030106660643,
      "longitude": 105.27644033103931
    }
  },
  {
    "ma": "MA468",
    "title": "Cylinker 468",
    "image": "image468.jpg",
    "location": {
      "latitude": 9.525986951396062,
      "longitude": 105.67296705306391
    }
  },
  {
    "ma": "MA469",
    "title": "Cylinker 469",
    "image": "image469.jpg",
    "location": {
      "latitude": 14.760272529081139,
      "longitude": 103.9167854845492
    }
  },
  {
    "ma": "MA470",
    "title": "Cylinker 470",
    "image": "image470.jpg",
    "location": {
      "latitude": 9.184984375429247,
      "longitude": 102.57536635390426
    }
  },
  {
    "ma": "MA471",
    "title": "Cylinker 471",
    "image": "image471.jpg",
    "location": {
      "latitude": 16.906054292373422,
      "longitude": 105.46827146062765
    }
  },
  {
    "ma": "MA472",
    "title": "Cylinker 472",
    "image": "image472.jpg",
    "location": {
      "latitude": 21.02564369316806,
      "longitude": 106.25717370763412
    }
  },
  {
    "ma": "MA473",
    "title": "Cylinker 473",
    "image": "image473.jpg",
    "location": {
      "latitude": 21.894049183789015,
      "longitude": 103.28352273628259
    }
  },
  {
    "ma": "MA474",
    "title": "Cylinker 474",
    "image": "image474.jpg",
    "location": {
      "latitude": 19.124542429985304,
      "longitude": 108.5215305428048
    }
  },
  {
    "ma": "MA475",
    "title": "Cylinker 475",
    "image": "image475.jpg",
    "location": {
      "latitude": 18.91383146777731,
      "longitude": 108.26417996083478
    }
  },
  {
    "ma": "MA476",
    "title": "Cylinker 476",
    "image": "image476.jpg",
    "location": {
      "latitude": 14.091356104203633,
      "longitude": 109.04107029751776
    }
  },
  {
    "ma": "MA477",
    "title": "Cylinker 477",
    "image": "image477.jpg",
    "location": {
      "latitude": 12.097429907212616,
      "longitude": 108.36205671287624
    }
  },
  {
    "ma": "MA478",
    "title": "Cylinker 478",
    "image": "image478.jpg",
    "location": {
      "latitude": 22.15624785081262,
      "longitude": 108.11966118550234
    }
  },
  {
    "ma": "MA479",
    "title": "Cylinker 479",
    "image": "image479.jpg",
    "location": {
      "latitude": 17.362104700612917,
      "longitude": 103.61220450947322
    }
  },
  {
    "ma": "MA480",
    "title": "Cylinker 480",
    "image": "image480.jpg",
    "location": {
      "latitude": 18.543390275244164,
      "longitude": 107.23758414605335
    }
  },
  {
    "ma": "MA481",
    "title": "Cylinker 481",
    "image": "image481.jpg",
    "location": {
      "latitude": 10.319517017265103,
      "longitude": 102.36398395687006
    }
  },
  {
    "ma": "MA482",
    "title": "Cylinker 482",
    "image": "image482.jpg",
    "location": {
      "latitude": 20.733861686786575,
      "longitude": 109.0355841584468
    }
  },
  {
    "ma": "MA483",
    "title": "Cylinker 483",
    "image": "image483.jpg",
    "location": {
      "latitude": 19.816160292646884,
      "longitude": 102.81758407606932
    }
  },
  {
    "ma": "MA484",
    "title": "Cylinker 484",
    "image": "image484.jpg",
    "location": {
      "latitude": 13.153763685461495,
      "longitude": 107.01795796417557
    }
  },
  {
    "ma": "MA485",
    "title": "Cylinker 485",
    "image": "image485.jpg",
    "location": {
      "latitude": 22.898989114350265,
      "longitude": 104.30903195306992
    }
  },
  {
    "ma": "MA486",
    "title": "Cylinker 486",
    "image": "image486.jpg",
    "location": {
      "latitude": 19.402997831457753,
      "longitude": 105.36825038826099
    }
  },
  {
    "ma": "MA487",
    "title": "Cylinker 487",
    "image": "image487.jpg",
    "location": {
      "latitude": 21.874975324671617,
      "longitude": 109.49732480351017
    }
  },
  {
    "ma": "MA488",
    "title": "Cylinker 488",
    "image": "image488.jpg",
    "location": {
      "latitude": 18.040320392054845,
      "longitude": 107.12491063535597
    }
  },
  {
    "ma": "MA489",
    "title": "Cylinker 489",
    "image": "image489.jpg",
    "location": {
      "latitude": 10.064597674355467,
      "longitude": 103.89145492817006
    }
  },
  {
    "ma": "MA490",
    "title": "Cylinker 490",
    "image": "image490.jpg",
    "location": {
      "latitude": 18.337278376063296,
      "longitude": 104.76210154034607
    }
  },
  {
    "ma": "MA491",
    "title": "Cylinker 491",
    "image": "image491.jpg",
    "location": {
      "latitude": 22.831505399707765,
      "longitude": 104.53882192932973
    }
  },
  {
    "ma": "MA492",
    "title": "Cylinker 492",
    "image": "image492.jpg",
    "location": {
      "latitude": 8.72483431659014,
      "longitude": 105.21595597237423
    }
  },
  {
    "ma": "MA493",
    "title": "Cylinker 493",
    "image": "image493.jpg",
    "location": {
      "latitude": 8.254894677903085,
      "longitude": 103.65612394148694
    }
  },
  {
    "ma": "MA494",
    "title": "Cylinker 494",
    "image": "image494.jpg",
    "location": {
      "latitude": 10.823223482358946,
      "longitude": 105.10260186747915
    }
  },
  {
    "ma": "MA495",
    "title": "Cylinker 495",
    "image": "image495.jpg",
    "location": {
      "latitude": 9.473225499509098,
      "longitude": 108.36306258614535
    }
  },
  {
    "ma": "MA496",
    "title": "Cylinker 496",
    "image": "image496.jpg",
    "location": {
      "latitude": 13.91483592092893,
      "longitude": 104.16590237591505
    }
  },
  {
    "ma": "MA497",
    "title": "Cylinker 497",
    "image": "image497.jpg",
    "location": {
      "latitude": 18.68520062135609,
      "longitude": 106.62273639563976
    }
  },
  {
    "ma": "MA498",
    "title": "Cylinker 498",
    "image": "image498.jpg",
    "location": {
      "latitude": 18.47777210677947,
      "longitude": 109.49317464520753
    }
  },
  {
    "ma": "MA499",
    "title": "Cylinker 499",
    "image": "image499.jpg",
    "location": {
      "latitude": 20.934267792114916,
      "longitude": 104.24027403376222
    }
  },
  {
    "ma": "MA500",
    "title": "Cylinker 500",
    "image": "image500.jpg",
    "location": {
      "latitude": 12.649643890449905,
      "longitude": 106.66907319947687
    }
  }
]